{
  "main": {
    "id": "9d071916f8e40ec5",
    "type": "split",
    "children": [
      {
        "id": "dd54912cad973075",
        "type": "tabs",
        "children": [
          {
            "id": "57167a1497339dfd",
            "type": "leaf",
            "state": {
              "type": "empty",
              "state": {},
              "icon": "lucide-file",
              "title": "新标签页"
            }
          }
        ]
      }
    ],
    "direction": "vertical"
  },
  "left": {
    "id": "0364283c716bee3b",
    "type": "split",
    "children": [
      {
        "id": "22c875f1707b6f1e",
        "type": "tabs",
        "children": [
          {
            "id": "c787413cef9981b7",
            "type": "leaf",
            "state": {
              "type": "file-explorer",
              "state": {
                "sortOrder": "alphabetical"
              },
              "icon": "lucide-folder-closed",
              "title": "文件列表"
            }
          },
          {
            "id": "e8eec65c3d5a4877",
            "type": "leaf",
            "state": {
              "type": "search",
              "state": {
                "query": "",
                "matchingCase": false,
                "explainSearch": false,
                "collapseAll": false,
                "extraContext": false,
                "sortOrder": "alphabetical"
              },
              "icon": "lucide-search",
              "title": "搜索"
            }
          },
          {
            "id": "c3d1798229af5af0",
            "type": "leaf",
            "state": {
              "type": "starred",
              "state": {},
              "icon": "lucide-file",
              "title": "插件不再活动"
            }
          },
          {
            "id": "a1e4aebe9e97a469",
            "type": "leaf",
            "state": {
              "type": "bookmarks",
              "state": {},
              "icon": "lucide-bookmark",
              "title": "书签"
            }
          }
        ]
      }
    ],
    "direction": "horizontal",
    "width": 300
  },
  "right": {
    "id": "531485005e3254a0",
    "type": "split",
    "children": [
      {
        "id": "0e2d6662880aa307",
        "type": "tabs",
        "children": [
          {
            "id": "b9ecb24f3d245a9a",
            "type": "leaf",
            "state": {
              "type": "backlink",
              "state": {
                "collapseAll": false,
                "extraContext": false,
                "sortOrder": "alphabetical",
                "showSearch": false,
                "searchQuery": "",
                "backlinkCollapsed": false,
                "unlinkedCollapsed": true
              },
              "icon": "links-coming-in",
              "title": "反向链接"
            }
          },
          {
            "id": "9318aaa63cb2549b",
            "type": "leaf",
            "state": {
              "type": "outgoing-link",
              "state": {
                "linksCollapsed": false,
                "unlinkedCollapsed": true
              },
              "icon": "links-going-out",
              "title": "出链"
            }
          },
          {
            "id": "56c87bd897082695",
            "type": "leaf",
            "state": {
              "type": "tag",
              "state": {
                "sortOrder": "frequency",
                "useHierarchy": true
              },
              "icon": "lucide-tags",
              "title": "标签"
            }
          },
          {
            "id": "c912f11ab1bdc346",
            "type": "leaf",
            "state": {
              "type": "outline",
              "state": {},
              "icon": "lucide-list",
              "title": "大纲"
            }
          }
        ],
        "currentTab": 3
      }
    ],
    "direction": "horizontal",
    "width": 300
  },
  "left-ribbon": {
    "hiddenItems": {
      "switcher:打开快速切换": false,
      "graph:查看关系图谱": false,
      "canvas:新建白板": false,
      "daily-notes:打开/创建今天的日记": false,
      "templates:插入模板": false,
      "command-palette:打开命令面板": false
    }
  },
  "active": "57167a1497339dfd",
  "lastOpenFiles": [
    "Other/i18n（国际化）地域标识码.md",
    "SUMMARY.md",
    "Other",
    "README.md",
    "Network-notes/单线复用.md",
    "RaspberryPi-notes/Gadgets-note.md",
    "2024-11-20.md",
    "未命名.canvas",
    "images/Pasted image 20231008165042.png",
    "images/Pasted image 20231008164814.png",
    "images/Pasted image 20231008164252.png",
    "images/Pasted image 20231008162822.png",
    "images/Pasted image 20231008160916.png",
    "images/Pasted image 20231008160617.png",
    "images/Pasted image 20231008160507.png",
    "images/Pasted image 20231008154338.png",
    "images/Pasted image 20231007215757.png",
    "images/1285132d4f833e8ff05c2cd1dc48c6d.jpg",
    "2023-10-08.md",
    "images",
    "Network-notes",
    "Cocos-notes/Cocos2d-js-note.md",
    "JS-notes/生成音频.md",
    "uniapp/微信小程序的图片预览兼容性处理.md",
    "Cocos-notes/Cocos-note.md",
    "VPS-notes/Google Drive笔记.md",
    "uniapp/swiper-item高度自适应.md",
    "RaspberryPi-notes/Ubuntu-RaspberryPi.md",
    "TypeScript-notes.md",
    "uniapp.md",
    "JS-notes/打印页面.md",
    "JS-notes/使用浏览器书签执行js代码.md",
    "JS-notes/字符串转换数组.md",
    "JS-notes/JSON.stringify的小技巧.md",
    "Linux-notes/linux常用指令.md",
    "Mobile-notes/移动端常用样式及兼容相关.md",
    "VUE-notes/vue-note.md",
    "VPS-notes/vps安全相关.md",
    "VPS-notes/Ubuntu笔记.md",
    "VPS-notes/ssh小记.md",
    "Windows-notes",
    "Web-notes",
    "VUE-notes",
    "VPS-notes",
    "TypeScript-notes",
    "TelegramBot-notes",
    "RaspberryPi-notes/img"
  ]
}